s3hero/__init__.py
s3hero/cli.py
s3hero/client.py
s3hero/config.py
s3hero/utils.py
s3hero-1.0.0.dist-info/licenses/LICENSE
s3hero-1.0.0.dist-info/METADATA
s3hero-1.0.0.dist-info/WHEEL
s3hero-1.0.0.dist-info/entry_points.txt
s3hero-1.0.0.dist-info/top_level.txt
s3hero-1.0.0.dist-info/RECORD
