Metadata-Version: 2.4
Name: s3hero
Version: 1.0.0
Summary: A powerful CLI tool to manage S3 buckets across AWS, Cloudflare R2, and S3-compatible services
Author-email: S3Hero Team <team@s3hero.dev>
License: MIT
Project-URL: Homepage, https://github.com/aravindgopall/s3hero
Project-URL: Documentation, https://github.com/aravindgopall/s3hero#readme
Project-URL: Repository, https://github.com/aravindgopall/s3hero
Project-URL: Issues, https://github.com/aravindgopall/s3hero/issues
Keywords: s3,aws,cloudflare,r2,cli,storage,bucket
Classifier: Development Status :: 5 - Production/Stable
Classifier: Environment :: Console
Classifier: Intended Audience :: Developers
Classifier: Intended Audience :: System Administrators
Classifier: License :: OSI Approved :: MIT License
Classifier: Operating System :: OS Independent
Classifier: Programming Language :: Python :: 3
Classifier: Programming Language :: Python :: 3.8
Classifier: Programming Language :: Python :: 3.9
Classifier: Programming Language :: Python :: 3.10
Classifier: Programming Language :: Python :: 3.11
Classifier: Programming Language :: Python :: 3.12
Classifier: Topic :: System :: Systems Administration
Classifier: Topic :: Utilities
Requires-Python: >=3.8
License-File: LICENSE
Requires-Dist: boto3>=1.28.0
Requires-Dist: click>=8.1.0
Requires-Dist: rich>=13.0.0
Requires-Dist: pyyaml>=6.0
Requires-Dist: humanize>=4.0.0
Requires-Dist: tqdm>=4.65.0
Provides-Extra: dev
Requires-Dist: pytest>=7.0.0; extra == "dev"
Requires-Dist: pytest-cov>=4.0.0; extra == "dev"
Requires-Dist: black>=23.0.0; extra == "dev"
Requires-Dist: ruff>=0.1.0; extra == "dev"
Requires-Dist: mypy>=1.0.0; extra == "dev"
Requires-Dist: types-PyYAML>=6.0.0; extra == "dev"
Dynamic: license-file
